fast_targetprice/__init__.py
fast_targetprice/dataset.json
fast_targetprice-0.1.3.dist-info/METADATA
fast_targetprice-0.1.3.dist-info/WHEEL
fast_targetprice-0.1.3.dist-info/top_level.txt
fast_targetprice-0.1.3.dist-info/RECORD
