Metadata-Version: 2.1
Name: fast_targetprice
Version: 0.1.3
Summary: Socket price CSGO
Author: Minh nguyen
Author-email: minh.worker.117@gmail.com
Classifier: Programming Language :: Python :: 3
Classifier: License :: OSI Approved :: MIT License
Classifier: Operating System :: OS Independent
Requires-Python: >=3.6
